django_cookies_samesite/__init__.py
django_cookies_samesite/middleware.py
django_cookies_samesite/models.py
django_cookies_samesite/user_agent_checker.py
django_cookies_samesite-0.7.0.dist-info/LICENSE
django_cookies_samesite-0.7.0.dist-info/METADATA
django_cookies_samesite-0.7.0.dist-info/WHEEL
django_cookies_samesite-0.7.0.dist-info/top_level.txt
django_cookies_samesite-0.7.0.dist-info/RECORD
