Metadata-Version: 2.1
Name: django-cookies-samesite
Version: 0.7.0
Summary: Middleware which sets SameSite flag for session and csrf cookies in legacy versions of Django.
Home-page: https://github.com/jotes/django-cookies-samesite
Author: Jarek "jotes" Śmiejczak
Author-email: poke@jotes.work
License: UNKNOWN
Keywords: django-cookies-samesite
Platform: UNKNOWN
Classifier: Development Status :: 3 - Alpha
Classifier: Framework :: Django :: 1.11
Classifier: Framework :: Django :: 2.0
Classifier: Framework :: Django :: 2.1
Classifier: Framework :: Django :: 2.2
Classifier: Intended Audience :: Developers
Classifier: Natural Language :: English
Classifier: Programming Language :: Python :: 2
Classifier: Programming Language :: Python :: 2.7
Classifier: Programming Language :: Python :: 3
Classifier: Programming Language :: Python :: 3.6
Classifier: Programming Language :: Python :: 3.7
Requires-Dist: ua-parser (==0.10.0)
